mge_lpips/__init__.py
mge_lpips/lpips.py
mge_lpips/pretrained_networks.py
mge_lpips/utils.py
mge_lpips/models/__init__.py
mge_lpips/models/alexnet.py
mge_lpips/models/squeezenet.py
mge_lpips/models/vgg.py
mge_lpips/weights/v0.0/alex.pth
mge_lpips/weights/v0.0/squeeze.pth
mge_lpips/weights/v0.0/vgg.pth
mge_lpips/weights/v0.1/alex.pth
mge_lpips/weights/v0.1/squeeze.pth
mge_lpips/weights/v0.1/vgg.pth
mge_lpips-0.1.0.dist-info/LICENSE
mge_lpips-0.1.0.dist-info/METADATA
mge_lpips-0.1.0.dist-info/WHEEL
mge_lpips-0.1.0.dist-info/top_level.txt
mge_lpips-0.1.0.dist-info/RECORD
