Metadata-Version: 2.1
Name: mge-lpips
Version: 0.1.0
Summary: LPIPS Similarity Metric for MegEngine
Home-page: https://github.com/insomnia250/MegEngine-LPIPS
Author: Chi Zhang
Author-email: zhangchi04@megvii.com
License: UNKNOWN
Platform: UNKNOWN
Classifier: Programming Language :: Python :: 3
Classifier: License :: OSI Approved :: BSD License
Classifier: Operating System :: OS Independent
Requires-Python: >3.5.0
License-File: LICENSE
Requires-Dist: torchvision
Requires-Dist: typing-extensions ; python_version == "3.6"
